ikfast_abb_irb4600_40_255.cp37-win_amd64.pyd
ikfast_eth_rfl.cp37-win_amd64.pyd
ikfast_franka_panda.cp37-win_amd64.pyd
ikfast_kawasaki_rs010n.cp37-win_amd64.pyd
ikfast_kuka_kr6_r900.cp37-win_amd64.pyd
ikfast_ur3.cp37-win_amd64.pyd
ikfast_ur5.cp37-win_amd64.pyd
ikfast_ur5e.cp37-win_amd64.pyd
ikfast_pybind-0.1.2.dist-info/AUTHORS.rst
ikfast_pybind-0.1.2.dist-info/LICENSE
ikfast_pybind-0.1.2.dist-info/METADATA
ikfast_pybind-0.1.2.dist-info/WHEEL
ikfast_pybind-0.1.2.dist-info/top_level.txt
ikfast_pybind-0.1.2.dist-info/RECORD
