Metadata-Version: 2.1
Name: ikfast-pybind
Version: 0.1.2
Summary: ikfast_pybind is a python binding generation library for the analytic kinematics engine ikfast.
Home-page: https://github.com/yijiangh/ikfast_pybind
Author: Yijiang Huang
Author-email: yijiangh@mit.edu
License: MIT License
Keywords: Robotics,kinematics
Classifier: Development Status :: 2 - Pre-Alpha
Classifier: Intended Audience :: Science/Research
Classifier: Topic :: Scientific/Engineering
Classifier: License :: OSI Approved :: MIT License
Classifier: Operating System :: Unix
Classifier: Operating System :: Microsoft :: Windows
Classifier: Programming Language :: Python
Classifier: Programming Language :: Python :: 2.7
Classifier: Programming Language :: Python :: 3
Classifier: Programming Language :: Python :: 3.3
Classifier: Programming Language :: Python :: 3.4
Classifier: Programming Language :: Python :: 3.5
Classifier: Programming Language :: Python :: 3.6
License-File: LICENSE
License-File: AUTHORS.rst
Requires-Dist: cmake (>=3.18)
